opik_installer/__init__.py
opik_installer/opik_constants.py
opik_installer/version.py
opik_installer/ansible/play.opik-deps.yml
opik_installer/ansible/play.opik.yml
opik_installer/ansible/roles/comet-minikube/defaults/main.yml
opik_installer/ansible/roles/comet-minikube/files/CentOS7-Extras.repo
opik_installer/ansible/roles/comet-minikube/files/comet-ml.sudoers
opik_installer/ansible/roles/comet-minikube/tasks/common.yml
opik_installer/ansible/roles/comet-minikube/tasks/darwin.yml
opik_installer/ansible/roles/comet-minikube/tasks/debian.yml
opik_installer/ansible/roles/comet-minikube/tasks/main.yml
opik_installer/ansible/roles/comet-minikube/tasks/uninstall_common.yml
opik_installer/ansible/roles/comet-minikube/tasks/uninstall_debian.yml
opik_installer/ansible/roles/comet-minikube/templates/kubernetes.repo.j2
opik_installer/ansible/roles/comet-minikube/templates/minikube.service.j2
opik_installer/ansible/roles/comet-opik/defaults/main.yml
opik_installer/ansible/roles/comet-opik/tasks/main.yml
opik_installer-1.0.5.dist-info/METADATA
opik_installer-1.0.5.dist-info/WHEEL
opik_installer-1.0.5.dist-info/entry_points.txt
opik_installer-1.0.5.dist-info/top_level.txt
opik_installer-1.0.5.dist-info/RECORD
